MANIFEST.in
reporter.py
setup.py
dlenv_pytorch_1_12_gpu_meta.egg-info/PKG-INFO
dlenv_pytorch_1_12_gpu_meta.egg-info/SOURCES.txt
dlenv_pytorch_1_12_gpu_meta.egg-info/dependency_links.txt
dlenv_pytorch_1_12_gpu_meta.egg-info/top_level.txt