Metadata-Version: 1.0
Name: dlenv-pytorch-1-12-gpu-meta
Version: 1.0.20230220
Summary: Ethical research - dep confusion package. This is not a real package, do not install.
Home-page: UNKNOWN
Author: UNKNOWN
Author-email: UNKNOWN
License: UNKNOWN
Platform: UNKNOWN
